VafabApi/Unofficial.py
VafabApi/UnofficialTypes.py
VafabApi/__init__.py
VafabApi-0.1.0.dist-info/LICENSE
VafabApi-0.1.0.dist-info/METADATA
VafabApi-0.1.0.dist-info/WHEEL
VafabApi-0.1.0.dist-info/top_level.txt
VafabApi-0.1.0.dist-info/RECORD
