Metadata-Version: 2.1
Name: VafabApi
Version: 0.1.0
Summary: Helper to get pickup times for garbage
Home-page: https://github.com/APayerl/VafabApi
Author: Anders Payerl
Author-email: anders_payerl@msn.com
License: MIT
Classifier: Intended Audience :: Developers
Classifier: License :: OSI Approved :: MIT License
Classifier: Programming Language :: Python
Classifier: Programming Language :: Python :: 3.9
Classifier: Programming Language :: Python :: 3.10
Classifier: Operating System :: OS Independent
License-File: LICENSE
Requires-Dist: dataclasses-json
Requires-Dist: requests
